dhutils/__init__.py
dhutils/print_functions.py
DHPyUtilPack-0.0.1.2.dist-info/LICENSE
DHPyUtilPack-0.0.1.2.dist-info/METADATA
DHPyUtilPack-0.0.1.2.dist-info/WHEEL
DHPyUtilPack-0.0.1.2.dist-info/top_level.txt
DHPyUtilPack-0.0.1.2.dist-info/RECORD
