Metadata-Version: 2.1
Name: DHPyUtilPack
Version: 0.0.1.2
Summary: Personal Python Package
Home-page: https://github.com/DongHoon5793/DH_PyPackage
Author: DongHoon Kim
Author-email: donghoon5793@gmail.com
License: UNKNOWN
Platform: UNKNOWN
Classifier: Programming Language :: Python :: 3
Classifier: License :: OSI Approved :: MIT License
Classifier: Operating System :: OS Independent
License-File: LICENSE
